[
  {
    "advertId": "34849647",
    "price": "219,50 M Ft",
    "district": "N/A",
    "area": "125 m2",
    "rooms": "4"
  },
  {
    "advertId": "34829279",
    "price": "170 M Ft",
    "district": "N/A",
    "area": "118 m2",
    "rooms": "4"
  },
  {
    "advertId": "34804923",
    "price": "170 M Ft",
    "district": "N/A",
    "area": "118 m2",
    "rooms": "4"
  },
  {
    "advertId": "34782974",
    "price": "214,90 M Ft",
    "district": "N/A",
    "area": "110 m2",
    "rooms": "4"
  },
  {
    "advertId": "34700444",
    "price": "214,90 M Ft",
    "district": "N/A",
    "area": "107 m2",
    "rooms": "4"
  },
  {
    "advertId": "34815108",
    "price": "206 M Ft",
    "district": "N/A",
    "area": "109 m2",
    "rooms": "5"
  },
  {
    "advertId": "34756750",
    "price": "210 M Ft",
    "district": "N/A",
    "area": "100 m2",
    "rooms": "3 + 1 fél"
  }
]